{
  "Account": "",
  "Average number of comments per post within the last 30 days": "",
  "Average number of reactions per post within the last 30 days. A reaction is a like or emoji": "",
  "Avg. Comments": "",
  "Avg. Reactions": "",
  "Cancel": "",
  "Comments": "",
  "Content": "",
  "Created": "",
  "Enter your website or blog URL": "",
  "Followers": "",
  "Likes": "",
  "Linking": "",
  "Ok": "",
  "Paste your {0} profile URL to link your account": "",
  "Please link your social media accounts to your profile. This helps us to review and manage your account": "",
  "Post": "",
  "Posts": "",
  "Profile": "",
  "Profile URL": "",
  "Shares": "",
  "Social media accounts": "",
  "Status": "",
  "Unlinking": "",
  "Views": ""
}
