{
    "Notify influencer?": "Notificar la influencia?",
    "Do you want to notify the influencer of this change?": "¿Quieres notificar al influencer de este cambio?",
    "Delete link?": "¿Borrar enlace?",
    "Delete the influencer's link?": "¿Eliminar el enlace del influencer?",
    "Approve": "Aprobar",
    "Cancel": "Cancelar",
    "Approving code": "Código de aprobación",
    "Please wait": "por favor espera",
    "Revoke": "Revocar",
    "Revoking code": "Revocando código",
    "Use this form to rename your influencer code and link. Please use only your new link/code. Your existing link and code will be deleted in {0} days": "Use este formulario para cambiar el nombre de su código de influencia y enlace. Utilice solo su nuevo enlace / código. Su enlace y código existentes se eliminarán en {0} días",
    "New code": "Nuevo código",
    "Rename code?": "Renombrar código?",
    "Invalid code": "Codigo invalido",
    "Changing code": "Cambiando codigo",
    "Codes": "Codigos",
    "This page lists your influencer's codes and their status. You can approve or revoke codes as required": "Esta página enumera los códigos de su influencer y su estado. Puede aprobar o revocar códigos según sea necesario",
    "This page lists your influencer codes and their status": "Esta página enumera sus códigos de influencia y su estado",
    "Approve selected codes": "Aprobar los códigos seleccionados",
    "Revoke selected codes": "Revocar códigos seleccionados",
    "Rename": "Rebautizar",
    "Actions": "Comportamiento",
    "No matches found": "No se encontraron coincidencias",
    "selected": "seleccionado",
    "Your code is": "Tu código es",
    "You have no codes": "No tienes codigos"
}