{
  "Account": "Cuenta",
  "Status": "Estado",
  "Profile": "Perfil",
  "Followers": "Seguidores",
  "Posts": "Mensajes",
  "Number of posts within the last 30 days": "Número de publicaciones en los últimos 30 días.",
  "Avg. Reactions": "Avg. Reacciones",
  "Average number of reactions per post within the last 30 days. A reaction is a like or emoji": "Número promedio de reacciones por publicación en los últimos 30 días. Una reacción es semejante o emoji.",
  "Avg. Comments": "Avg. Comentarios",
  "Average number of comments per post within the last 30 days": "Número promedio de comentarios por publicación en los últimos 30 días"
}
