{
  "Log into PayPal and fix your account": "PayPalにログインしてアカウントを修正する",
  "Your PayPal account is valid": "あなたのPayPalアカウントは有効です",
  "Your PayPal account setup is incomplete. You must log into your PayPal account and resolve any issues before you can be paid commission": "あなたのPayPalアカウントの設定は不完全です。あなたがPayPalアカウントにログインし、あなたが手数料を支払うことができる前に問題を解決しなければなりません",
  "Check": "チェック",
  "This influencer can not be paid until they resolve their PayPal account issues": "このインフルエンサーは、彼らが彼らのPayPalアカウントの問題を解決するまで支払うことができません",
  "Overview": "概要",
  "Marketing accounts": "マーケティングアカウント",
  "When you link a social media account with us, we use the following information": "あなたが私たちとソーシャルメディアアカウントをリンクするとき、私たちは以下の情報を使います",
  "Your basic public info": "あなたの基本的な公開情報",
  "Metrics that measure your marketing reach/engagment. I.e. # of followers": "あなたのマーケティングリーチ/エンゲージメントを測定する指標。すなわちフォロワー数",
  "Important": "重要",
  "We do not use or store any other information and we do not share your info": "私たちは他のいかなる情報も使用または保存せず、またあなたの情報を共有しません。",
  "Discount Codes": "割引コード",
  "Links": "リンク集",
  "This table lists your influencer discount code and link. For details on how to use your link or code and; create product or collection specific referral links, see the": "この表はあなたのインフルエンサーディスカウントコードとリンクをリストしています。リンクやコードの使い方の詳細については、製品またはコレクション固有の紹介リンクを作成します。",
  "How do I use my link and discount code": "リンクとディスカウントコードの使い方",
  "section of our guide": "ガイドのセクション",
  "Orders": "ご注文",
  "Show": "見せる",
  "Leads": "見込み客",
  "Notes": "ノート",
  "Save": "保存する",
  "Leads (clicks)": "見込み客（クリック）",
  "Leads (unique)": "リード（ユニーク）",
  "Sales": "売上高",
  "Conv rate": "コンバージョン率",
  "New": "新しい",
  "Returning": "戻る",
  "Ratio": "比率",
  "Owed": "所有している",
  "Paid": "有料",
  "Lead sources": "リードソース",
  "Sales by customer": "顧客別売上",
  "Earnings": "収益"
}
