{
  "Name": "名称",
  "Email": "电子邮件",
  "Location": "地点",
  "Status": "状态",
  "Your account is pending our approval. This may take up to 48 hours.": "您的帐户正在等待我们的批准。这可能需要长达48小时。",
  "Group": "组",
  "Link": "链接",
  "Code": "码",
  "Details": "细节",
  "Influencer": "影响",
  "Performance": "性能",
  "Leads": "信息",
  "Orders": "命令",
  "Revenue": "收入",
  "Commission": "佣金",
  "Earned": "挣",
  "Owed": "欠",
  "Payable": "应付帐款",
  "Commission can only be paid for orders that that are paid, fulfilled and at least {0} days old": "只有支付，履行且至少{0}天的订单才能支付佣金",
  "Paid": "付费",
  "Meta": "元",
  "Created At": "创建于"
}
